rst2pptx
